{
  "parent": "advancednetherite:nether/netherite_emerald_armor",
  "criteria": {
    "netherite_diamond_armor": {
      "conditions": {
        "items": [
          {
            "items": "advancednetherite:netherite_diamond_helmet"
          },
          {
            "items": "advancednetherite:netherite_diamond_chestplate"
          },
          {
            "items": "advancednetherite:netherite_diamond_leggings"
          },
          {
            "items": "advancednetherite:netherite_diamond_boots"
          }
        ]
      },
      "trigger": "minecraft:inventory_changed"
    }
  },
  "display": {
    "description": {
      "translate": "advancements.advancednetherite.nether.netherite_diamond_armor.description"
    },
    "frame": "challenge",
    "icon": {
      "count": 1,
      "id": "advancednetherite:netherite_diamond_chestplate"
    },
    "title": {
      "translate": "advancements.advancednetherite.nether.netherite_diamond_armor.title"
    }
  },
  "requirements": [
    [
      "netherite_diamond_armor"
    ]
  ],
  "rewards": {
    "experience": 200
  },
  "sends_telemetry_event": true
}